sphinx_needs_data_explorer/__init__.py
sphinx_needs_data_explorer/_static/_static/js/explorer_button.js
sphinx_needs_data_explorer/_static/_templates/article-header-buttons.html
sphinx_needs_data_explorer/_static/_templates/explorer-button.html
sphinx_needs_data_explorer/_static/jquery/LICENSE.txt
sphinx_needs_data_explorer/_static/jquery/jquery-3.7.1.min
sphinx_needs_data_explorer/_static/peg/LICENSE.txt
sphinx_needs_data_explorer/_static/peg/peg-0.10.0.min.js
sphinx_needs_data_explorer/_static/select2/LICENSE.md
sphinx_needs_data_explorer/_static/select2/package.json
sphinx_needs_data_explorer/_static/select2/select2.min.css
sphinx_needs_data_explorer/_static/select2/select2.min.js
sphinx_needs_data_explorer/_static/sphinx_needs_data_explorer.css
sphinx_needs_data_explorer/_static/sphinx_needs_data_explorer.html
sphinx_needs_data_explorer/_static/sphinx_needs_data_explorer.js
sphinx_needs_data_explorer/_static/vis-network/LICENSE-APACHE-2.0
sphinx_needs_data_explorer/_static/vis-network/LICENSE-MIT
sphinx_needs_data_explorer/_static/vis-network/package.json
sphinx_needs_data_explorer/_static/vis-network/vis-network.min.js
sphinx_needs_data_explorer/_static/vis-network/vis-network.min.js.map
sphinx_needs_data_explorer-0.9.6.dist-info/LICENSE
sphinx_needs_data_explorer-0.9.6.dist-info/METADATA
sphinx_needs_data_explorer-0.9.6.dist-info/WHEEL
sphinx_needs_data_explorer-0.9.6.dist-info/RECORD
