Metadata-Version: 2.1
Name: sphinx_needs_data_explorer
Version: 0.9.6
Summary: Sphinx-needs-data-explorer is a Sphinx extension to visualize Sphinx-Needs data
Home-page: https://github.com/mi-parkes/sphinx-needs-data-explorer
License: MIT
Author: Michael Parkes
Author-email: mparkes@post.cz
Requires-Python: >=3.10,<4.0
Classifier: License :: OSI Approved :: MIT License
Classifier: Programming Language :: Python :: 3
Classifier: Programming Language :: Python :: 3.10
Classifier: Programming Language :: Python :: 3.11
Classifier: Programming Language :: Python :: 3.12
Requires-Dist: Sphinx (>=6.1.3)
Project-URL: Documentation, https://mi-parkes.github.io/sphinx-needs-data-explorer/
Project-URL: Repository, https://github.com/mi-parkes/sphinx-needs-data-explorer
